{
    "currentVersion": {
        "created": "2019-03-20 15:53:25",
        "template_version": "eabb7df1-823a-11e9-af35-0eaa5a9daa9c"
    },
    "prevVersions": [],
    "template_id": "RPT50633",
    "selectedVersion": "eabb7df1-823a-11e9-af35-0eaa5a9daa9c",
    "is_public": "1",
    "TLAP_Approved": null,
    "published_at": "2019-03-20 15:53:25",
    "title": "MR Brain - Dementia",
    "template_status": null,
    "description": " ",
    "author": "rsna_00456600",
    "firstname": "Mark",
    "lastname": "Mamlouk",
    "originalAuthor": "rsna_00456600",
    "originalAuthorFirstname": "Mark",
    "originalAuthorLastName": "Mamlouk",
    "views": "1378",
    "downloads": "4502",
    "created": "2019-03-20 15:53:25",
    "dataType": "html",
    "reviewInProgress": "1",
    "englishName": "English",
    "langCode": "en",
    "favCount": "2",
    "templateData": "<html><head><meta charset=\"UTF-8\"><meta content=\"base mri brain dementia\" name=\"dcterms.title\"><meta content=\"b0e5f940-1324-4666-80f7-aeda4839c33a\" name=\"dcterms.identifier\"><meta content=\"en\" name=\"dcterms.language\"><meta content=\"2019-01-31\" name=\"dcterms.date\"><meta content=\"Nuance System\" name=\"dcterms.creator\"><title>base mri brain dementia</title></head><body><section data-section-name=\"MRI BRAIN WITHOUT CONTRAST\"><header class=\"Level1\">MRI BRAIN WITHOUT CONTRAST</header><p><label>HISTORY:</label><input type=\"text\" name=\"Patient Age\" value=\"Patient Age\"></p><p><label> old </label><input type=\"text\" name=\"Patient Gender\" value=\"Patient Gender\"></p><p><label>, </label><input type=\"text\" name=\"history\" value=\"dementia\"></p></section><section data-section-name=\"TECHNIQUE:\"><header class=\"Level1\">TECHNIQUE:</header><p><label>MR images of the brain were acquired without intravenous contrast.</label><br><label>COMPARISON: </label><input type=\"text\" name=\"Comparison\" value=\"None available.\"></p></section><section data-section-name=\"FINDINGS:\"><header class=\"Level1\">FINDINGS:</header><p><label>BRAIN VOLUME: </label><select name=\"atrophy\"><option name=\"\" value=\"\">No age-significant</option><option name=\"\" value=\"\">Mild</option><option name=\"\" value=\"\">Moderate</option><option name=\"\" value=\"\">Severe</option></select></p><p><label> atrophy. </label><select name=\"location\"><option name=\"\" value=\"\" selected=\"\">Global without lobar predilection or asymmetry.</option><option name=\"regional\" value=\"regional\">Regional atrophy,    </option><option name=\"\" value=\"\" selected=\"\"></option></select></p><p><label>HIPPOCAMPAL VOLUME: </label><select name=\"hippocampal volume\"><option name=\"\" value=\"\">Normal.</option><option name=\"\" value=\"\">Mildly reduced.</option><option name=\"\" value=\"\">Moderately reduced.</option><option name=\"\" value=\"\">Severely reduced.</option></select></p><p><label>BRAINSTEM/CEREBELLUM: </label><input type=\"text\" name=\"brainstem cerebellum\" value=\"Normal volume and signal intensity. No imaging findings of progressive supranuclear palsy, multiple system atrophy, or other primary cerebellar neurodegenerative condition.\"></p><p><label>CORTEX/BASAL GANGLIA: </label><input type=\"text\" name=\"cortext basal ganglia\" value=\"No evidence of prior insult, abnormal mineralization, prion disease, or autoimmune encephalitis.\"></p></section><section data-section-name=\"ISCHEMIA:\"><header class=\"Level1\">ISCHEMIA:</header><p><label>Infarction: </label><input type=\"text\" name=\"infarct, attention angular gyrus, thalamus, basal forebrain, PCA territory, ACA territory\" value=\"None.\"></p><p><label>Chronic Small Vessel Disease: </label><select name=\"WM, with attention to the deep component]\"><option name=\"\" value=\"\">Absent.</option><option name=\"\" value=\"\">Mild.</option><option name=\"\" value=\"\">Moderate.</option><option name=\"\" value=\"\">Severe.</option></select></p><p><label>CEREBRAL MICROHEMORRHAGES: </label><input type=\"text\" name=\"microhemorrhage, attention location and pattern\" value=\"None.\"></p><p><label>MASS: </label><input type=\"text\" name=\"mass?\" value=\"None.\"></p><p><label>VENTRICLES: </label><select name=\"ventricles\"><option name=\"\" value=\"\">No hydrocephalus.</option><option name=\"\" value=\"\">Ex-vacuo dilatation.</option><option name=\"Hydrocephalus\" value=\"Hydrocephalus\">Hydrocephalus,    </option></select></p><p><label>EXTRA-AXIAL FLUID COLLECTIONS: </label><input type=\"text\" name=\"extra-axial\" value=\"None.\"></p><p><label>OTHER: </label><input type=\"text\" name=\"other\" value=\"None\"></p></section><section data-section-name=\"IMPRESSION:\"><header class=\"Level1\">IMPRESSION:</header><p><textarea name=\"impression\">Normal MRI brain.</textarea></p></section></body></html>",
    "organizations": [
        {
            "id": "284",
            "name": "Kaiser Permanente",
            "code": null
        }
    ],
    "specialty": [
        {
            "code": "HN",
            "name": "Head and Neck"
        },
        {
            "code": "NR",
            "name": "Neuroradiology"
        },
        {
            "code": "MR",
            "name": "Magnetic Resonance Imaging"
        }
    ],
    "coauthors": [],
    "cdeSets": [],
    "translators": [],
    "references": [],
    "procedures": [
        {
            "procedure_id": "30657-1",
            "procedure_name": "MR Brain WO contrast",
            "source": "LOINC"
        }
    ],
    "radlex": [],
    "isFavorite": "0"
}