{
    "currentVersion": {
        "created": "2018-11-20 08:42:07",
        "template_version": "e1ccdb9e-814f-11e9-af35-0eaa5a9daa9c"
    },
    "prevVersions": [],
    "template_id": "RPT50515",
    "selectedVersion": "e1ccdb9e-814f-11e9-af35-0eaa5a9daa9c",
    "is_public": "1",
    "TLAP_Approved": null,
    "published_at": "2018-11-20 08:42:07",
    "title": "CT Chest wo Contrast",
    "template_status": null,
    "description": "CT Chest wo Contrast",
    "author": "rsna_00326615",
    "firstname": "Marta",
    "lastname": "Heilbrun",
    "originalAuthor": "rsna_00326615",
    "originalAuthorFirstname": "Marta",
    "originalAuthorLastName": "Heilbrun",
    "views": "7625",
    "downloads": "7483",
    "created": "2018-11-20 08:42:07",
    "dataType": "html",
    "reviewInProgress": null,
    "englishName": "English",
    "langCode": "en",
    "favCount": "4",
    "templateData": "<!DOCTYPE html>\n<html>\n    <head>\n        <title>Chest CT Without Contrast</title>\n        <meta charset=\"UTF-8\" />\n        <meta name=\"dcterms.identifier\" content=\"318f7c58-6d0f-4695-bc86-bd5ed0a271b4\" />\n        <meta name=\"dcterms.title\" content=\"Chest CT Without Contrast\" />\n        <meta name=\"dcterms.description\" content=\"\" />\n        <meta name=\"dcterms.type\" content=\"IMAGE_REPORT_TEMPLATE\" />\n        <meta name=\"dcterms.language\" content=\"en\" />\n        <meta name=\"dcterms.publisher\" content=\"University of Utah\" />\n        <meta name=\"dcterms.rights\" content=\"May be used freely, subject to license agreement\" />\n        <meta name=\"dcterms.license\" content=\"http://www.radreport.org/license.pdf\" />\n        <meta name=\"dcterms.date\" content=\"2018-05-20\" />\n        <meta name=\"dcterms.creator\" content=\"Howard Mann\" />\n        <script type=\"text/xml\">\n            <template_attributes>\n                <coded_content>\n                    <coding_schemes>\n                        <coding_scheme name=\"RADLEX\" designator=\"2.16.840.1.113883.6.256\"></coding_scheme>\n                        <coding_scheme name=\"LOINC\" designator=\"2.16.840.1.113883.6.1\"></coding_scheme>\n                    </coding_schemes>\n                    <entry origtxt=\"findings\">\n                        <term>\n                            <code meaning=\"Procedure Findings\" value=\"59776-5\" scheme=\"LOINC\"></code>\n                        </term>\n                    </entry>\n                    <entry origtxt=\"impressionText\">\n                        <term>\n                            <code meaning=\"normal\" value=\"RID13173\" scheme=\"RADLEX\"></code>\n                        </term>\n                    </entry>\n                    <entry origtxt=\"TEXT_1459374926054\">\n                        <term>\n                            <code meaning=\"heart\" value=\"RID1385\" scheme=\"RADLEX\"></code>\n                        </term>\n                    </entry>\n                    <entry origtxt=\"findingsText\">\n                        <term>\n                            <code meaning=\"lungs\" value=\"RID13437\" scheme=\"RADLEX\"></code>\n                        </term>\n                    </entry>\n                    <entry origtxt=\"TEXT_1459374926053\">\n                        <term>\n                            <code meaning=\"pleural space\" value=\"RID1363\" scheme=\"RADLEX\"></code>\n                        </term>\n                    </entry>\n                    <entry origtxt=\"TEXT_1459374926056\">\n                        <term>\n                            <code meaning=\"set of chest vessels\" value=\"RID49962\" scheme=\"RADLEX\"></code>\n                        </term>\n                    </entry>\n                    <entry origtxt=\"TEXT_1459374926055\">\n                        <term>\n                            <code meaning=\"mediastinum\" value=\"RID1384\" scheme=\"RADLEX\"></code>\n                        </term>\n                    </entry>\n                    <entry origtxt=\"procedureInformation\">\n                        <term>\n                            <code meaning=\"Current Imaging Procedure Description\" value=\"55111-9\" scheme=\"LOINC\"></code>\n                        </term>\n                    </entry>\n                    <entry origtxt=\"TEXT_1459374926057\">\n                        <term>\n                            <code meaning=\"chest wall\" value=\"RID2468\" scheme=\"RADLEX\"></code>\n                        </term>\n                    </entry>\n                    <entry origtxt=\"comparisons\">\n                        <term>\n                            <code meaning=\"Radiology Comparison Study\" value=\"18834-2\" scheme=\"LOINC\"></code>\n                        </term>\n                    </entry>\n                    <entry origtxt=\"impression\">\n                        <term>\n                            <code meaning=\"Impressions\" value=\"19005-8\" scheme=\"LOINC\"></code>\n                        </term>\n                    </entry>\n                    <entry origtxt=\"clinicalInformation\">\n                        <term>\n                            <code meaning=\"Clinical Information\" value=\"55752-0\" scheme=\"LOINC\"></code>\n                        </term>\n                    </entry>\n                    <entry origtxt=\"SELECTION_LIST_1459374926059\">\n                        <term>\n                            <code meaning=\"upper abdomen\" value=\"RID29990\" scheme=\"RADLEX\"></code>\n                        </term>\n                    </entry>\n                    <entry origtxt=\"TEXT_1459374926052\">\n                        <term>\n                            <code meaning=\"clinical information section\" value=\"RID13166\" scheme=\"RADLEX\"></code>\n                        </term>\n                    </entry>\n                </coded_content>\n            </template_attributes>\n        </script>\n    </head>\n    <body>\n        <section id=\"procedureInformation\" class=\"level1\" data-section-name=\"Procedure Information\">\n            <header class=\"level1\">\n                Procedure Information\n            </header>\n            <p title=\"\">\n                <label for=\"procedureInformationText\">Technique:</label>\n                <textarea rows=\"3\" cols=\"100\" id=\"procedureInformationText\" name=\"\" data-field-type=\"TEXTAREA\" data-field-completion-action=\"NONE\">Non-Enhanced Multidetector-Row Chest Computed Tomography. Axial (5mm; 1mm; 10mm MIPS); Coronal (3mm); and Sagittal (3mm) series were acquired.</textarea>\n            </p>\n        </section>\n        <section id=\"clinicalInformation\" class=\"level1\" data-section-name=\"Clinical Information\">\n            <header class=\"level1\">\n                Clinical Information\n            </header>\n            <p title=\"\">\n                <label for=\"TEXT_1459374926052\">Indication:</label>\n                <textarea rows=\"3\" cols=\"100\" id=\"TEXT_1459374926052\" name=\"\" data-field-type=\"TEXTAREA\" data-field-completion-action=\"NONE\">None.</textarea>\n            </p>\n        </section>\n        <section id=\"comparisons\" class=\"level1\" data-section-name=\"Comparison\">\n            <header class=\"level1\">\n                Comparison\n            </header>\n            <p title=\"\">\n                <label for=\"comparisonsText\"></label>\n                <textarea rows=\"3\" cols=\"100\" id=\"comparisonsText\" name=\"\" data-field-type=\"TEXTAREA\" data-field-completion-action=\"NONE\">None.</textarea>\n            </p>\n        </section>\n        <section id=\"findings\" class=\"level1\" data-section-name=\"Findings\">\n            <header class=\"level1\">\n                Findings\n            </header>\n            <p title=\"\">\n                <label for=\"findingsText\">Pulmonary Parenchyma and Airways:</label>\n                <textarea rows=\"3\" cols=\"100\" id=\"findingsText\" name=\"\" data-field-type=\"TEXTAREA\" data-field-completion-action=\"NONE\">No pulmonary parenchymal or airway process is present.</textarea>\n            </p>\n            <p title=\"\">\n                <label for=\"TEXT_1459374926053\">Pleural Space:</label>\n                <textarea rows=\"3\" cols=\"100\" id=\"TEXT_1459374926053\" name=\"\" data-field-type=\"TEXTAREA\" data-field-completion-action=\"NONE\">No pleural fluid or thickening is present.</textarea>\n            </p>\n            <p title=\"\">\n                <label for=\"TEXT_1459374926054\">Heart and Pericardium:</label>\n                <textarea rows=\"3\" cols=\"100\" id=\"TEXT_1459374926054\" name=\"\" data-field-type=\"TEXTAREA\" data-field-completion-action=\"NONE\">The cardiac chambers are normal in size. No pericardial fluid or thickening is present.</textarea>\n            </p>\n            <p title=\"\">\n                <label for=\"TEXT_1459374926055\">Mediastinum and Hila:</label>\n                <textarea rows=\"3\" cols=\"100\" id=\"TEXT_1459374926055\" name=\"\" data-field-type=\"TEXTAREA\" data-field-completion-action=\"NONE\">No mediastinal mass is present. No enlarged lymph nodes are present.</textarea>\n            </p>\n            <p title=\"\">\n                <label for=\"TEXT_1459374926056\">Thoracic Vessels:</label>\n                <textarea rows=\"3\" cols=\"100\" id=\"TEXT_1459374926056\" name=\"\" data-field-type=\"TEXTAREA\" data-field-completion-action=\"NONE\">No vascular abnormality is present.</textarea>\n            </p>\n            <p title=\"\">\n                <label for=\"TEXT_1459374926057\">Osseous Structures and Chest Wall:</label>\n                <textarea rows=\"3\" cols=\"100\" id=\"TEXT_1459374926057\" name=\"\" data-field-type=\"TEXTAREA\" data-field-completion-action=\"NONE\">No pathologic osseous or soft-tissue process is present.</textarea>\n            </p>\n            <p title=\"\">\n                <label for=\"SELECTION_LIST_1459374926059\">Upper Abdomen:</label>\n                <select id=\"SELECTION_LIST_1459374926059\" name=\"\" data-field-type=\"SELECTION_LIST\" data-field-completion-action=\"NONE\" value=\"No pathologic process is present in the imaged portion of the upper abdomen.\">\n                    <option id=\"SELECTION_LIST_1459374926059_0\" value=\"No pathologic process is present in the imaged portion of the upper abdomen.\" name=\"SELECTION_LIST_1459374926059\" selected=\"\">No pathologic process is present in the imaged portion of the upper abdomen.</option>\n                    <option id=\"SELECTION_LIST_1459374926059_1\" value=\"Imaging findings in the abdomen and pelvis are reported separately.\" name=\"SELECTION_LIST_1459374926059\">Imaging findings in the abdomen and pelvis are reported separately.</option>\n                </select>\n            </p>\n            <p title=\"\">\n                <label for=\"TEXT_1476460383686\">Additional findings:</label>\n                <textarea rows=\"3\" cols=\"100\" id=\"TEXT_1476460383686\" name=\"\" data-field-type=\"TEXTAREA\" data-field-completion-action=\"NONE\">None.</textarea>\n            </p>\n        </section>\n        <section id=\"impression\" class=\"level1\" data-section-name=\"Impression\">\n            <header class=\"level1\">\n                Impression\n            </header>\n            <p title=\"\">\n                <label for=\"impressionText\"></label>\n                <textarea rows=\"3\" cols=\"100\" id=\"impressionText\" name=\"\" data-field-type=\"TEXTAREA\" data-field-completion-action=\"NONE\">Normal.</textarea>\n            </p>\n        </section>\n    </body>\n</html>\n",
    "organizations": [
        {
            "id": "277",
            "name": "University of Utah",
            "code": "Utah"
        }
    ],
    "specialty": [
        {
            "code": "CT",
            "name": "Computed Tomography"
        },
        {
            "code": "CH",
            "name": "Chest Radiology"
        }
    ],
    "coauthors": [],
    "cdeSets": [],
    "translators": [],
    "references": [],
    "procedures": [],
    "radlex": [],
    "isFavorite": "0"
}